weblate_fonts/__init__.py
weblate_fonts/apps.py
weblate_fonts/py.typed
weblate_fonts/static/weblate_fonts/kurinto/ttf/KurintoSans-Bd.ttf
weblate_fonts/static/weblate_fonts/kurinto/ttf/KurintoSans-Rg.ttf
weblate_fonts/static/weblate_fonts/kurinto/ttf/KurintoSansJP-Bd.ttf
weblate_fonts/static/weblate_fonts/kurinto/ttf/KurintoSansJP-Rg.ttf
weblate_fonts/static/weblate_fonts/kurinto/ttf/KurintoSansKR-Bd.ttf
weblate_fonts/static/weblate_fonts/kurinto/ttf/KurintoSansKR-Rg.ttf
weblate_fonts/static/weblate_fonts/kurinto/ttf/KurintoSansSC-Bd.ttf
weblate_fonts/static/weblate_fonts/kurinto/ttf/KurintoSansSC-Rg.ttf
weblate_fonts/static/weblate_fonts/kurinto/ttf/KurintoSansTC-Bd.ttf
weblate_fonts/static/weblate_fonts/kurinto/ttf/KurintoSansTC-Rg.ttf
weblate_fonts/static/weblate_fonts/source-code/ttf/SourceCodePro-Black.ttf
weblate_fonts/static/weblate_fonts/source-code/ttf/SourceCodePro-BlackIt.ttf
weblate_fonts/static/weblate_fonts/source-code/ttf/SourceCodePro-Bold.ttf
weblate_fonts/static/weblate_fonts/source-code/ttf/SourceCodePro-BoldIt.ttf
weblate_fonts/static/weblate_fonts/source-code/ttf/SourceCodePro-ExtraLight.ttf
weblate_fonts/static/weblate_fonts/source-code/ttf/SourceCodePro-ExtraLightIt.ttf
weblate_fonts/static/weblate_fonts/source-code/ttf/SourceCodePro-It.ttf
weblate_fonts/static/weblate_fonts/source-code/ttf/SourceCodePro-Light.ttf
weblate_fonts/static/weblate_fonts/source-code/ttf/SourceCodePro-LightIt.ttf
weblate_fonts/static/weblate_fonts/source-code/ttf/SourceCodePro-Medium.ttf
weblate_fonts/static/weblate_fonts/source-code/ttf/SourceCodePro-MediumIt.ttf
weblate_fonts/static/weblate_fonts/source-code/ttf/SourceCodePro-Regular.ttf
weblate_fonts/static/weblate_fonts/source-code/ttf/SourceCodePro-Semibold.ttf
weblate_fonts/static/weblate_fonts/source-code/ttf/SourceCodePro-SemiboldIt.ttf
weblate_fonts/static/weblate_fonts/source-code/woff2/SourceCodePro-Black.ttf.woff2
weblate_fonts/static/weblate_fonts/source-code/woff2/SourceCodePro-BlackIt.ttf.woff2
weblate_fonts-2026.1.dist-info/licenses/LICENSES/CC0-1.0.txt
weblate_fonts-2026.1.dist-info/licenses/LICENSES/OFL-1.1.txt
weblate_fonts-2026.1.dist-info/WHEEL
weblate_fonts-2026.1.dist-info/METADATA
weblate_fonts-2026.1.dist-info/RECORD
