Metadata-Version: 2.4
Name: weblate-fonts
Version: 2026.1
Summary: Weblate fonts collection
Keywords: gettext,git,i18n,l10n,mercurial,translate
Author: Michal Čihař
Author-email: Michal Čihař <michal@weblate.org>
License-Expression: OFL-1.1
License-File: LICENSES/CC0-1.0.txt
License-File: LICENSES/OFL-1.1.txt
Classifier: Development Status :: 5 - Production/Stable
Classifier: Intended Audience :: Developers
Classifier: Operating System :: OS Independent
Classifier: Programming Language :: Python :: 3 :: Only
Classifier: Programming Language :: Python :: 3
Classifier: Programming Language :: Python :: 3.11
Classifier: Programming Language :: Python :: 3.12
Classifier: Programming Language :: Python :: 3.13
Classifier: Programming Language :: Python :: 3.14
Classifier: Programming Language :: Python
Classifier: Topic :: Software Development :: Internationalization
Classifier: Topic :: Software Development :: Localization
Classifier: Topic :: Utilities
Requires-Python: >=3.11
Project-URL: Documentation, https://docs.weblate.org/
Project-URL: Download, https://github.com/WeblateOrg/fonts
Project-URL: Funding, https://weblate.org/donate/
Project-URL: Homepage, https://weblate.org/
Project-URL: Issue Tracker, https://github.com/WeblateOrg/fonts/issues
Project-URL: Source Code, https://github.com/WeblateOrg/fonts
Project-URL: Twitter, https://twitter.com/WeblateOrg
